{ 
	"head": {
		"heading": { 
			"text": "Партньори" 
		}, 
		
		"text": [ 
			{ 
				"text": "Нашето високвалифицирано обслужване и огромен брой доволни клиенти не биха били възможни без любезното съдействие, съвети и помощ на нашите партньори." 
			}
		]
	}, 

	"body": { 
		"template": "block.html", 
		"level": 3, 

		"entries": [ 
			{ 
				"subheading": { 
					"text": "Вносител" 
				}, 
				"heading": { 
					"text": "Condex" 
				}, 
				"text": [], 
				"link": { 
					"text": "Прочетете повече" 
				}
			}

		]

	}

}